mistral_ocr/__init__.py
mistral_ocr/core.py
mistral_ocr/gui.py
mistral_ocr/widgets.py
mistral_ocr_gui-0.4.0.dist-info/licenses/LICENSE
mistral_ocr_gui-0.4.0.dist-info/METADATA
mistral_ocr_gui-0.4.0.dist-info/WHEEL
mistral_ocr_gui-0.4.0.dist-info/entry_points.txt
mistral_ocr_gui-0.4.0.dist-info/top_level.txt
mistral_ocr_gui-0.4.0.dist-info/RECORD
