Metadata-Version: 2.4
Name: mistral-ocr-gui
Version: 0.4.0
Summary: A graphical user interface for processing images with the Mistral OCR API.
Author: Danielnara24
License-Expression: MIT
Project-URL: Homepage, https://github.com/Danielnara24/Mistral-OCR
Classifier: Programming Language :: Python :: 3
Classifier: Operating System :: OS Independent
Classifier: Topic :: Scientific/Engineering :: Image Recognition
Classifier: Environment :: Win32 (MS Windows)
Requires-Python: >=3.8
License-File: LICENSE
Requires-Dist: mistralai
Requires-Dist: tkinterdnd2
Requires-Dist: Pillow
Dynamic: license-file
